[
    {
        "parent_id": null,
        "nama": "Pranata Lab. Pendidikan",
        "kode": "",
        "ikhtisar": "Ikhtisar Pranata Lab. Pendidikan",
        "prestasi": ""
    },
    {
        "parent_id": null,
        "nama": "Pengelola Informasi Akademik",
        "kode": "",
        "ikhtisar": "Ikhtisar Pengelola Informasi Akademik",
        "prestasi": ""
    },
    {
        "parent_id": null,
        "nama": "Pengadministrasi Perpustakaan",
        "kode": "",
        "ikhtisar": "Ikhtisar Pengadministrasi Perpustakaan",
        "prestasi": ""
    },
    {
        "parent_id": null,
        "nama": "Pengelola Barang Milik Negara",
        "kode": "",
        "ikhtisar": "Ikhtisar Pengelola Barang Milik Negara",
        "prestasi": ""
    },
    {
        "parent_id": null,
        "nama": "Pustakawan",
        "kode": "",
        "ikhtisar": "Ikhtisar Pustakawan",
        "prestasi": ""
    },
    {
        "parent_id": null,
        "nama": "Pengelola Gaji",
        "kode": "",
        "ikhtisar": "Ikhtisar Pengelola Gaji",
        "prestasi": ""
    },
    {
        "parent_id": null,
        "nama": "Pengolah data",
        "kode": "",
        "ikhtisar": "Ikhtisar Pengolah data",
        "prestasi": ""
    },
    {
        "parent_id": null,
        "nama": "Pengadministrasi Akademik",
        "kode": "",
        "ikhtisar": "Ikhtisar Pengadministrasi Akademik",
        "prestasi": ""
    },
    {
        "parent_id": null,
        "nama": "Pengelola Perbendaharaan dan Pelayanan",
        "kode": "",
        "ikhtisar": "Ikhtisar Pengelola Perbendaharaan dan Pelayanan",
        "prestasi": ""
    },
    {
        "parent_id": null,
        "nama": "Teknisi Lab.",
        "kode": "",
        "ikhtisar": "Ikhtisar Teknisi Lab.",
        "prestasi": ""
    },
    {
        "parent_id": null,
        "nama": "Pengelola Keuangan",
        "kode": "",
        "ikhtisar": "Ikhtisar Pengelola Keuangan",
        "prestasi": ""
    },
    {
        "parent_id": null,
        "nama": "Pengolah data Pengelolaan Keuangan",
        "kode": "",
        "ikhtisar": "Ikhtisar Pengolah data Pengelolaan Keuangan",
        "prestasi": ""
    },
    {
        "parent_id": null,
        "nama": "Pramu Bakti",
        "kode": "",
        "ikhtisar": "Ikhtisar Pramu Bakti",
        "prestasi": ""
    },
    {
        "parent_id": null,
        "nama": "Pengadministrasi Keuangan",
        "kode": "",
        "ikhtisar": "Ikhtisar Pengadministrasi Keuangan",
        "prestasi": ""
    },
    {
        "parent_id": null,
        "nama": "Teknisi Peralatan Kantor",
        "kode": "",
        "ikhtisar": "Ikhtisar Teknisi Peralatan Kantor",
        "prestasi": ""
    },
    {
        "parent_id": null,
        "nama": "Pengelola Informasi Akademik",
        "kode": "",
        "ikhtisar": "Ikhtisar Pengelola Informasi Akademik",
        "prestasi": ""
    },
    {
        "parent_id": null,
        "nama": "Pembuat Daftar Gaji",
        "kode": "",
        "ikhtisar": "Ikhtisar Pembuat Daftar Gaji",
        "prestasi": ""
    },
    {
        "parent_id": null,
        "nama": "Penyusun Laporan Keuangan",
        "kode": "",
        "ikhtisar": "Ikhtisar Penyusun Laporan Keuangan",
        "prestasi": ""
    },
    {
        "parent_id": null,
        "nama": "Pengelola Sistem dan Jaringan",
        "kode": "",
        "ikhtisar": "Ikhtisar Pengelola Sistem dan Jaringan",
        "prestasi": ""
    },
    {
        "parent_id": null,
        "nama": "Pengolah data Tenaga Kependidikan",
        "kode": "",
        "ikhtisar": "Ikhtisar Pengolah data Tenaga Kependidikan",
        "prestasi": ""
    },
    {
        "parent_id": null,
        "nama": "Pengadministrasi Layanan Kegiatan Kemahasiswaan",
        "kode": "",
        "ikhtisar": "Ikhtisar Pengadministrasi Layanan Kegiatan Kemahasiswaan",
        "prestasi": ""
    },
    {
        "parent_id": null,
        "nama": "Pengolah Data Program, Anggaran, dan Laporan Keuangan",
        "kode": "",
        "ikhtisar": "Ikhtisar Pengolah Data Program, Anggaran, dan Laporan Keuangan",
        "prestasi": ""
    },
    {
        "parent_id": null,
        "nama": "Pengadministrasi barang milik Negara",
        "kode": "",
        "ikhtisar": "Ikhtisar Pengadministrasi barang milik Negara",
        "prestasi": ""
    },
    {
        "parent_id": null,
        "nama": "Penyusun dokumen Perencanaan",
        "kode": "",
        "ikhtisar": "Ikhtisar Penyusun dokumen Perencana",
        "prestasi": ""
    },
    {
        "parent_id": null,
        "nama": "Penyusun Program Anggaran dan Pelaporan",
        "kode": "",
        "ikhtisar": "Ikhtisar Penyusun Program Anggaran dan Pelaporan",
        "prestasi": ""
    },
    {
        "parent_id": null,
        "nama": "Sekretaris",
        "kode": "",
        "ikhtisar": "Ikhtisar Sekretaris",
        "prestasi": ""
    },
    {
        "parent_id": null,
        "nama": "Teknisi Komputer",
        "kode": "",
        "ikhtisar": "Ikhtisar Teknisi Komputer",
        "prestasi": ""
    },
    {
        "parent_id": null,
        "nama": "Pengadministrasi data Peraturan perundang-undangan",
        "kode": "",
        "ikhtisar": "Ikhtisar Pengadministrasi data Peraturan perundang-undangan",
        "prestasi": ""
    },
    {
        "parent_id": null,
        "nama": "Pengadministrasi Kepegawaian",
        "kode": "",
        "ikhtisar": "Ikhtisar Pengadministrasi Kepegawaian",
        "prestasi": ""
    },
    {
        "parent_id": null,
        "nama": "Petugas Kearsipan",
        "kode": "",
        "ikhtisar": "Ikhtisar Petugas Kearsipan",
        "prestasi": ""
    },
    {
        "parent_id": null,
        "nama": "Petugas Humas",
        "kode": "",
        "ikhtisar": "Ikhtisar Petugas Humas",
        "prestasi": ""
    }
]
